nametable/Animator.py
nametable/Block.py
nametable/Nametable.py
nametable/Pattern.py
nametable/PatternAnimated.py
nametable/PatternMeta.py
nametable/PatternTable.py
nametable/PatternTableAnimated.py
nametable/__init__.py
tests/__init__.py
tests/conftest.py
tests/test_block.py
tests/test_nametable.py
tests/test_pattern.py
tests/test_pattern_animator.py
tests/test_pattern_meta.py
tests/test_pattern_table.py
tests/test_pattern_table_animated.py
nametable-0.2.0.dist-info/LICENSE
nametable-0.2.0.dist-info/METADATA
nametable-0.2.0.dist-info/WHEEL
nametable-0.2.0.dist-info/top_level.txt
nametable-0.2.0.dist-info/RECORD
