Metadata-Version: 2.1
Name: nametable
Version: 0.2.0
Summary: An OOP approach to represent nametables on the NES
Author: IsaiahASmith
Author-email: isaiah@clsolutions.ltd
License: GPL3
Requires-Python: <3.14,>=3.12.0
License-File: LICENSE
Requires-Dist: numpy>=1.21.2
Provides-Extra: dev
Requires-Dist: black>=21.7b0; extra == "dev"
Requires-Dist: pytest>=6.2.4; extra == "dev"
Requires-Dist: flake8>=3.9.2; extra == "dev"
Requires-Dist: pydata-sphinx-theme>=0.6.3; extra == "dev"
Requires-Dist: numpydoc>=1.1.0; extra == "dev"
Requires-Dist: hypothesis>=6.23.1; extra == "dev"
Requires-Dist: Sphinx>=4.2.0; extra == "dev"
